README.rst
setup.py
Django_api_base.egg-info/PKG-INFO
Django_api_base.egg-info/SOURCES.txt
Django_api_base.egg-info/dependency_links.txt
Django_api_base.egg-info/requires.txt
Django_api_base.egg-info/top_level.txt
django_api_base/__init__.py
django_api_base/admin.py
django_api_base/api_base.py
django_api_base/logging_conf.py
django_api_base/models.py
django_api_base/utils.py
django_api_base/middleware/__init__.py
django_api_base/middleware/api_exception.py
django_api_base/middleware/logging_middleware.py
django_api_base/migrations/0001_initial.py
django_api_base/migrations/0002_auto_20170823_1006.py
django_api_base/migrations/0003_auto_20220621_0732.py
django_api_base/migrations/__init__.py