Metadata-Version: 2.1
Name: Django-api-base
Version: 1.1.0
Summary: A simple Django app to make the RESTFULL APIs
Home-page: https://maneeshv.github.io
Author: Maneesh Shaji
Author-email: maneeshvettukattil@gmail.com
License: MIT
Platform: UNKNOWN
Classifier: Environment :: Web Environment
Classifier: Framework :: Django
Classifier: Framework :: Django :: 1.11
Classifier: Intended Audience :: Developers
Classifier: License :: OSI Approved :: BSD License
Classifier: Programming Language :: Python
Classifier: Programming Language :: Python :: 3
Classifier: Topic :: Internet :: WWW/HTTP
Classifier: Topic :: Internet :: WWW/HTTP :: Dynamic Content
